bayspar/__init__.py
bayspar/plot.py
bayspar/predict.py
bayspar/utils.py
bayspar/example_data/castaneda2010.csv
bayspar/example_data/lopes_santos2010.csv
bayspar/example_data/shevenell2011.csv
bayspar/example_data/wilsonlake.csv
bayspar/modelparams/__init__.py
bayspar/modelparams/core.py
bayspar/modelparams/Output_SpatAg_SST/Locs_Comp.mat
bayspar/modelparams/Output_SpatAg_SST/alpha_samples_comp.mat
bayspar/modelparams/Output_SpatAg_SST/beta_samples_comp.mat
bayspar/modelparams/Output_SpatAg_SST/tau2_samples.mat
bayspar/modelparams/Output_SpatAg_subT/Locs_Comp.mat
bayspar/modelparams/Output_SpatAg_subT/alpha_samples_comp.mat
bayspar/modelparams/Output_SpatAg_subT/beta_samples_comp.mat
bayspar/modelparams/Output_SpatAg_subT/tau2_samples.mat
bayspar/observations/Data_Input_SpatAg_SST.mat
bayspar/observations/Data_Input_SpatAg_subT.mat
bayspar/observations/__init__.py
bayspar/observations/core.py
bayspar/observations/locs_woa_1degree_asvec_SST.mat
bayspar/observations/locs_woa_1degree_asvec_subT.mat
bayspar/observations/st_woa_1degree_asvec_SST.mat
bayspar/observations/st_woa_1degree_asvec_subT.mat
bayspar/tests/__init__.py
bayspar/tests/test_modelparams.py
bayspar/tests/test_observations.py
bayspar/tests/test_predict.py
bayspar/tests/test_utils.py
baysparpy-0.0.3.dist-info/DESCRIPTION.rst
baysparpy-0.0.3.dist-info/METADATA
baysparpy-0.0.3.dist-info/RECORD
baysparpy-0.0.3.dist-info/WHEEL
baysparpy-0.0.3.dist-info/metadata.json
baysparpy-0.0.3.dist-info/top_level.txt
