Metadata-Version: 2.0
Name: baysparpy
Version: 0.0.3
Summary: An Open Source Python package for TEX86 calibration
Home-page: https://github.com/brews/baysparpy
Author: S. Brewster Malevich
Author-email: malevich@email.arizona.edu
License: GPLv3
Keywords: marine paleoclimate tex86 calibration
Platform: UNKNOWN
Classifier: Development Status :: 3 - Alpha
Classifier: Intended Audience :: Developers
Classifier: Intended Audience :: Science/Research
Classifier: Topic :: Scientific/Engineering
Classifier: License :: OSI Approved :: GNU General Public License v3 or later (GPLv3+)
Classifier: Programming Language :: Python :: 3
Requires-Dist: numpy
Requires-Dist: scipy
Requires-Dist: matplotlib
Requires-Dist: attrs
Requires-Dist: tqdm
Requires-Dist: cartopy
